{
	"conditions_list": [
		{
			"icon": "clock",
			"name": "4 часа",
			"text": "Минимальное время проведенное за игрой 4 часа в сутки."
		},

		{
			"icon": "chip",
			"name": "Ставки",
			"text": "Уровень ставок должен соответствовать выбранному туру. С минимальными ставками вы можете ознакомиться в таблице выше."
		},
		{
			"icon": "crown",
			"name": "Программы лояльности",
			"text": "Уровень ставок должен соответствовать выбранному туру. С минимальными ставками вы можете ознакомиться в таблице выше."
		}
	]
}
